{
  "comments": [
    {
      "title": "Angular net",
      "body": "Angular is used for server side web applications",
      "author": "code with vina",
      "id": 2
    },
    {
      "title": "react net",
      "body": "react is used for server side web applications",
      "author": "code with kunu",
      "id": 3
    },
    {
      "title": "mongo net",
      "body": "node is used for server side web applications",
      "author": "code with tushi",
      "id": 4
    },
    {
      "title": "hie",
      "body": "hieeee piya",
      "author": "piya",
      "id": 5
    },
    {
      "title": "hie",
      "body": "hellooo",
      "author": "vina",
      "id": 6
    },
    {
      "title": "hie",
      "body": "hellooo",
      "author": "vina",
      "id": 7
    },
    {
      "title": "hie",
      "body": "hellooo",
      "author": "vina",
      "id": 8
    },
    {
      "title": "hie",
      "body": "hellooo",
      "author": "vina",
      "id": 9
    },
    {
      "title": "hie",
      "body": "hellooo",
      "author": "vina",
      "id": 10
    },
    {
      "title": "hie",
      "body": "hellooo",
      "author": "vina",
      "id": 11
    },
    {
      "title": "hie",
      "body": "hellooo",
      "author": "vina",
      "id": 12
    },
    {
      "title": "hie",
      "body": "hellooo",
      "author": "vina",
      "id": 13
    },
    {
      "title": "hie",
      "body": "hellooo",
      "author": "vina",
      "id": 14
    },
    {
      "title": "hi",
      "body": "hm",
      "author": "piya",
      "id": 15
    },
    {
      "title": "hi",
      "body": "hm",
      "author": "piya",
      "id": 16
    },
    {
      "title": "hi",
      "body": "hm",
      "author": "piya",
      "id": 17
    },
    {
      "title": "hi",
      "body": "hm",
      "author": "piya",
      "id": 18
    },
    {
      "title": "hi",
      "body": "hm",
      "author": "piya",
      "id": 19
    },
    {
      "title": "hi",
      "body": "hm",
      "author": "piya",
      "id": 20
    },
    {
      "title": "data upload",
      "body": "uploading.......",
      "author": "vina",
      "id": 21
    },
    {
      "title": "data upload",
      "body": "uploading.......",
      "author": "vina",
      "id": 22
    },
    {
      "title": "data upload",
      "body": "uploading.......",
      "author": "vina",
      "id": 23
    },
    {
      "title": "data upload",
      "body": "uploading.......",
      "author": "vina",
      "id": 24
    },
    {
      "title": "data upload",
      "body": "uploading.......",
      "author": "vina",
      "id": 25
    },
    {
      "title": "data upload",
      "body": "uploading.......",
      "author": "vina",
      "id": 26
    },
    {
      "title": "data upload",
      "body": "uploading data ",
      "author": "vina",
      "id": 27
    },
    {
      "title": "data upload",
      "body": "uploading data ",
      "author": "vina",
      "id": 28
    },
    {
      "title": "data",
      "body": "angular",
      "author": "vina",
      "id": 29
    },
    {
      "title": "hi",
      "body": "hmm",
      "author": "vina",
      "id": 30
    }
  ]
}